apiverve_urltitle/__init__.py
apiverve_urltitle/apiClient.py
apiverve_urltitle/exceptions.py
apiverve_urltitle/setup.py
apiverve_urltitle/setup_dep.py
apiverve_urltitle/tests/__init__.py
apiverve_urltitle/tests/test_api.py
apiverve_urltitle-1.1.5.dist-info/LICENSE
apiverve_urltitle-1.1.5.dist-info/METADATA
apiverve_urltitle-1.1.5.dist-info/WHEEL
apiverve_urltitle-1.1.5.dist-info/top_level.txt
apiverve_urltitle-1.1.5.dist-info/RECORD
